{
  "generated_at": "2026-03-29T20:28:53.121125",
  "input_path": "data/processed/daikin_clean.csv",
  "feature_policy_mode": "enhanced_onestep",
  "selected_target_strategy": "log1p_both",
  "walk_forward_tuned_params": {
    "electricity": {
      "n_estimators": 2200,
      "learning_rate": 0.02,
      "max_depth": 6,
      "subsample": 0.8,
      "colsample_bytree": 0.75,
      "min_child_weight": 10,
      "reg_alpha": 0.2,
      "reg_lambda": 2.0,
      "gamma": 0.1,
      "random_state": 42,
      "n_jobs": -1,
      "early_stopping_rounds": 120,
      "eval_metric": "mae"
    },
    "heat": {
      "n_estimators": 2600,
      "learning_rate": 0.015,
      "max_depth": 7,
      "subsample": 0.85,
      "colsample_bytree": 0.8,
      "min_child_weight": 8,
      "reg_alpha": 0.1,
      "reg_lambda": 1.8,
      "gamma": 0.05,
      "random_state": 42,
      "n_jobs": -1,
      "early_stopping_rounds": 150,
      "eval_metric": "mae"
    }
  },
  "split_diagnostics": {
    "train_rows": 16344,
    "test_rows": 4415,
    "train_max_timestamp": "2024-06-20 09:00:00+00:00",
    "test_min_timestamp": "2024-06-20 10:00:00+00:00",
    "overlap_timestamp_count": 0,
    "overlap_sample": [],
    "valid_time_split": true
  },
  "feature_schema_path": "models/feature_schema_v20260329_202819_102731_enhanced_onestep.json",
  "feature_schema": {
    "timestamp_column": "timestamp",
    "id_column": "system_id",
    "targets": [
      "heatpump_elec",
      "heatpump_heat"
    ],
    "electricity_features_ordered": [
      "heatpump_outsideT",
      "outsideT_3h_avg",
      "hdh",
      "heatpump_roomT",
      "temp_deficit",
      "load_ratio",
      "capacity_kw",
      "hour_sin",
      "hour_cos",
      "month_sin",
      "month_cos",
      "day_of_week",
      "is_heating_season",
      "elec_lag1",
      "elec_lag24",
      "elec_lag168",
      "elec_lag1_pct",
      "elec_lag2",
      "elec_lag3",
      "elec_lag4",
      "elec_lag6",
      "flowT_lag1",
      "returnT_lag1",
      "deltaT_house_lag1",
      "deltaT_lift_lag1",
      "lift_per_kw_lag1",
      "flowrate_lag1",
      "heating_on_lag1",
      "heating_on_lag24",
      "run_hours",
      "cop_lag1",
      "was_defrost_lag1"
    ],
    "heat_features_ordered": [
      "heatpump_outsideT",
      "outsideT_3h_avg",
      "hdh",
      "heatpump_roomT",
      "temp_deficit",
      "load_ratio",
      "capacity_kw",
      "hour_sin",
      "hour_cos",
      "month_sin",
      "month_cos",
      "day_of_week",
      "is_heating_season",
      "elec_lag1",
      "elec_lag24",
      "elec_lag168",
      "elec_lag1_pct",
      "elec_lag2",
      "elec_lag3",
      "elec_lag4",
      "elec_lag6",
      "flowT_lag1",
      "returnT_lag1",
      "deltaT_house_lag1",
      "deltaT_lift_lag1",
      "lift_per_kw_lag1",
      "flowrate_lag1",
      "heating_on_lag1",
      "heating_on_lag24",
      "run_hours",
      "cop_lag1",
      "was_defrost_lag1",
      "heat_lag1",
      "heat_lag24",
      "heat_lag168"
    ],
    "all_serving_features_ordered": [
      "heatpump_outsideT",
      "outsideT_3h_avg",
      "hdh",
      "heatpump_roomT",
      "temp_deficit",
      "load_ratio",
      "capacity_kw",
      "hour_sin",
      "hour_cos",
      "month_sin",
      "month_cos",
      "day_of_week",
      "is_heating_season",
      "elec_lag1",
      "elec_lag24",
      "elec_lag168",
      "elec_lag1_pct",
      "elec_lag2",
      "elec_lag3",
      "elec_lag4",
      "elec_lag6",
      "flowT_lag1",
      "returnT_lag1",
      "deltaT_house_lag1",
      "deltaT_lift_lag1",
      "lift_per_kw_lag1",
      "flowrate_lag1",
      "heating_on_lag1",
      "heating_on_lag24",
      "run_hours",
      "cop_lag1",
      "was_defrost_lag1",
      "heat_lag1",
      "heat_lag24",
      "heat_lag168"
    ],
    "feature_dtypes": {
      "heatpump_outsideT": "float",
      "outsideT_3h_avg": "float",
      "hdh": "float",
      "heatpump_roomT": "float",
      "temp_deficit": "float",
      "load_ratio": "float",
      "capacity_kw": "float",
      "hour_sin": "float",
      "hour_cos": "float",
      "month_sin": "float",
      "month_cos": "float",
      "day_of_week": "int",
      "is_heating_season": "int",
      "elec_lag1": "float",
      "elec_lag24": "float",
      "elec_lag168": "float",
      "elec_lag1_pct": "float",
      "elec_lag2": "float",
      "elec_lag3": "float",
      "elec_lag4": "float",
      "elec_lag6": "float",
      "flowT_lag1": "float",
      "returnT_lag1": "float",
      "deltaT_house_lag1": "float",
      "deltaT_lift_lag1": "float",
      "lift_per_kw_lag1": "float",
      "flowrate_lag1": "float",
      "heating_on_lag1": "float",
      "heating_on_lag24": "float",
      "run_hours": "int",
      "cop_lag1": "float",
      "was_defrost_lag1": "float",
      "heat_lag1": "float",
      "heat_lag24": "float",
      "heat_lag168": "float"
    },
    "required_serving_columns": [
      "heatpump_outsideT",
      "outsideT_3h_avg",
      "hdh",
      "heatpump_roomT",
      "temp_deficit",
      "load_ratio",
      "capacity_kw",
      "hour_sin",
      "hour_cos",
      "month_sin",
      "month_cos",
      "day_of_week",
      "is_heating_season",
      "elec_lag1",
      "elec_lag24",
      "elec_lag168",
      "elec_lag1_pct",
      "elec_lag2",
      "elec_lag3",
      "elec_lag4",
      "elec_lag6",
      "flowT_lag1",
      "returnT_lag1",
      "deltaT_house_lag1",
      "deltaT_lift_lag1",
      "lift_per_kw_lag1",
      "flowrate_lag1",
      "heating_on_lag1",
      "heating_on_lag24",
      "run_hours",
      "cop_lag1",
      "was_defrost_lag1",
      "heat_lag1",
      "heat_lag24",
      "heat_lag168"
    ]
  },
  "features": {
    "electricity": [
      "heatpump_outsideT",
      "outsideT_3h_avg",
      "hdh",
      "heatpump_roomT",
      "temp_deficit",
      "load_ratio",
      "capacity_kw",
      "hour_sin",
      "hour_cos",
      "month_sin",
      "month_cos",
      "day_of_week",
      "is_heating_season",
      "elec_lag1",
      "elec_lag24",
      "elec_lag168",
      "elec_lag1_pct",
      "elec_lag2",
      "elec_lag3",
      "elec_lag4",
      "elec_lag6",
      "flowT_lag1",
      "returnT_lag1",
      "deltaT_house_lag1",
      "deltaT_lift_lag1",
      "lift_per_kw_lag1",
      "flowrate_lag1",
      "heating_on_lag1",
      "heating_on_lag24",
      "run_hours",
      "cop_lag1",
      "was_defrost_lag1"
    ],
    "heat": [
      "heatpump_outsideT",
      "outsideT_3h_avg",
      "hdh",
      "heatpump_roomT",
      "temp_deficit",
      "load_ratio",
      "capacity_kw",
      "hour_sin",
      "hour_cos",
      "month_sin",
      "month_cos",
      "day_of_week",
      "is_heating_season",
      "elec_lag1",
      "elec_lag24",
      "elec_lag168",
      "elec_lag1_pct",
      "elec_lag2",
      "elec_lag3",
      "elec_lag4",
      "elec_lag6",
      "flowT_lag1",
      "returnT_lag1",
      "deltaT_house_lag1",
      "deltaT_lift_lag1",
      "lift_per_kw_lag1",
      "flowrate_lag1",
      "heating_on_lag1",
      "heating_on_lag24",
      "run_hours",
      "cop_lag1",
      "was_defrost_lag1",
      "heat_lag1",
      "heat_lag24",
      "heat_lag168"
    ]
  },
  "targets": [
    "heatpump_elec",
    "heatpump_heat"
  ],
  "models": {
    "electricity": "models/xgb_elec_v20260329_202819_102731_enhanced_onestep.json",
    "heat": "models/xgb_heat_v20260329_202819_102731_enhanced_onestep.json"
  },
  "metrics": {
    "r2_elec": 0.6806632649241229,
    "r2_heat": 0.6839546695998339,
    "mae_elec_w": 83.96137256015388,
    "mae_heat_w": 223.1434950518921,
    "true_elec_kwh": 637.62278819318,
    "pred_elec_kwh": 714.1436993738278,
    "true_heat_kwh": 2213.615119615806,
    "pred_heat_kwh": 2087.5136265880315,
    "energy_err_pct": 12.000968691455284,
    "heat_err_pct": 5.696631357020222,
    "true_cop": 3.471668768126194,
    "pred_cop": 2.9231002505775736,
    "cop_err_pct": 15.801291948848736,
    "cop_physical_valid_pct": 100.0,
    "cop_physical_invalid_count": 0,
    "cop_adjusted_count": 0,
    "off_forced_count": 3431,
    "runtime_false_negative_count": 0,
    "leakage_flag": false
  },
  "strategy_scores": [
    {
      "strategy": "log1p_both",
      "score_total_mae": 2045.5941363598793,
      "mae_elec_w": 399.58692163838145,
      "mae_heat_w": 1646.0072147214978
    },
    {
      "strategy": "cop_ratio_heat",
      "score_total_mae": 2349.464132103912,
      "mae_elec_w": 514.3317805590266,
      "mae_heat_w": 1835.1323515448855
    },
    {
      "strategy": "none",
      "score_total_mae": 2444.789424506207,
      "mae_elec_w": 514.3317805590266,
      "mae_heat_w": 1930.4576439471807
    }
  ],
  "slice_error_analysis_top10": [
    {
      "system_id": 162,
      "capacity_kw": 6,
      "rows": 2281,
      "mae_elec_w": 482.2379372871424,
      "mae_heat_w": 2154.0149939340267,
      "r2_elec": -2.8042172490999175,
      "r2_heat": -4.341242706652589
    },
    {
      "system_id": 44,
      "capacity_kw": 8,
      "rows": 828,
      "mae_elec_w": 383.34669424825864,
      "mae_heat_w": 1678.630358705223,
      "r2_elec": -0.43033967010284235,
      "r2_heat": -0.8576207320838398
    },
    {
      "system_id": 364,
      "capacity_kw": 8,
      "rows": 200,
      "mae_elec_w": 365.73661044088186,
      "mae_heat_w": 1551.8362214490385,
      "r2_elec": -0.06764474274386778,
      "r2_heat": -0.04148451298428024
    },
    {
      "system_id": 228,
      "capacity_kw": 4,
      "rows": 1013,
      "mae_elec_w": 436.6331868490349,
      "mae_heat_w": 1391.2456900354293,
      "r2_elec": -1.800487495487436,
      "r2_heat": -1.8608772392734299
    },
    {
      "system_id": 351,
      "capacity_kw": 6,
      "rows": 93,
      "mae_elec_w": 266.1906273771171,
      "mae_heat_w": 1283.7291722022699,
      "r2_elec": -0.5909822871149992,
      "r2_heat": -0.9447857001088567
    }
  ],
  "slice_calibrator_count": 3,
  "classifier": {
    "confusion_matrix": [
      [
        3431,
        0
      ],
      [
        0,
        984
      ]
    ],
    "classification_report": "              precision    recall  f1-score   support\n\n         OFF     1.0000    1.0000    1.0000      3431\n          ON     1.0000    1.0000    1.0000       984\n\n    accuracy                         1.0000      4415\n   macro avg     1.0000    1.0000    1.0000      4415\nweighted avg     1.0000    1.0000    1.0000      4415\n",
    "tn": 3431,
    "fp": 0,
    "fn": 0,
    "tp": 984
  },
  "gates": {
    "science_gates": {
      "r2_elec_pass": false,
      "r2_heat_pass": false,
      "mae_elec_pass": true,
      "mae_heat_pass": false
    },
    "business_gates": {
      "energy_err_pass": false,
      "heat_err_pass": false,
      "cop_err_pass": false,
      "cop_physical_pass": true,
      "leakage_pass": true,
      "runtime_fn_pass": true
    },
    "summary": {
      "science_overall_pass": false,
      "business_overall_pass": false,
      "production_ready_pass": false,
      "research_ready_pass": false
    }
  },
  "pipeline_artifacts": {
    "runtime_model": "models/xgb_runtime_clf_v20260329_202819_102731_enhanced_onestep.joblib",
    "electricity_imputer": "models/imputer_elec_v20260329_202819_102731_enhanced_onestep.joblib",
    "heat_imputer": "models/imputer_heat_v20260329_202819_102731_enhanced_onestep.joblib",
    "pipeline_meta": "models/pipeline_meta_v20260329_202819_102731_enhanced_onestep.json",
    "slice_calibrators": "models/slice_calibrators_v20260329_202819_102731_enhanced_onestep.json",
    "target_strategy": "log1p_both"
  },
  "imputer_strategy": {
    "electricity": "median_fit_train_only",
    "heat": "median_fit_train_only"
  }
}